README.md
setup.cfg
setup.py
airwaves/__init__.py
airwaves/aapb.py
airwaves/cli.py
airwaves/config.py
airwaves/upload.py
airwaves.egg-info/PKG-INFO
airwaves.egg-info/SOURCES.txt
airwaves.egg-info/dependency_links.txt
airwaves.egg-info/entry_points.txt
airwaves.egg-info/requires.txt
airwaves.egg-info/top_level.txt