Metadata-Version: 1.2
Name: airwaves
Version: 0.0.5
Summary: Unlocking the Airwaves Utilities
Home-page: https://github.com/umd_mith/airwaves
Author: Ed Summers
Author-email: ehs@pobox.com
License: UNKNOWN
Platform: UNKNOWN
Requires-Python: >=2.7
